convert_subnet/__init__.py
convert_subnet/convert_subnet.py
convert_subnet-3.1.2.dist-info/LICENSE
convert_subnet-3.1.2.dist-info/METADATA
convert_subnet-3.1.2.dist-info/WHEEL
convert_subnet-3.1.2.dist-info/entry_points.txt
convert_subnet-3.1.2.dist-info/top_level.txt
convert_subnet-3.1.2.dist-info/RECORD
