Metadata-Version: 2.1
Name: convert-subnet
Version: 3.1.2
Summary: convert_subnet: Convert Prefix Length To Subnet Mask & Vice-Versa
Home-page: https://github.com/VietDuc19
Author: LongDT15
Author-email: longdt15@fpt.com.vn
License: MIT
Keywords: network subnet_mask Prefix_Length CIDR Suffix
Classifier: Programming Language :: Python :: 3
Classifier: License :: OSI Approved :: MIT License
Classifier: Operating System :: OS Independent
License-File: LICENSE
Requires-Dist: subnetinfo
Requires-Dist: setuptools
